{
  "template": "utility-page",
  "lang": "ru",
  "slug": "about",
  "path": "about",
  "outputPath": "ru/about/index.html",
  "data": {
    "meta": {
      "title": "О Feeltracker | Ведущие приложения для отслеживания здоровья с ИИ для iOS",
      "description": "Feeltracker — ведущий набор приложений для отслеживания здоровья с ИИ для iOS. Наш трекер артериального давления — приложение №1 в Великобритании для мониторинга сердечно-сосудистой системы. Узнайте о наших 5 приложениях для здоровья, которыми пользуются более 500 000 человек по всему миру на 33 языках.",
      "keywords": "feeltracker, приложения для здоровья, приложение для давления, номер 1 Великобритания, трекер настроения, трекер веса, трекер сна, ежедневный дневник, ИИ приложения для здоровья",
      "ogTitle": "О Feeltracker | Приложение №1 для давления в Великобритании",
      "ogDescription": "Ведущие приложения для отслеживания здоровья с ИИ: артериальное давление, настроение, вес, сон и дневник. Более 500 000 пользователей по всему миру.",
      "ogImage": "https://feeltracker.com/images/feeltracker.png",
      "twitterDescription": ""
    },
    "structuredDataHtml": "    <script type=\"application/ld+json\">\n    {\n      \"@context\": \"https://schema.org\",\n      \"@type\": \"Organization\",\n      \"name\": \"Feeltracker\",\n      \"alternateName\": \"Custom Arts\",\n      \"url\": \"https://feeltracker.com\",\n      \"logo\": \"https://feeltracker.com/images/feeltracker.png\",\n      \"description\": \"Разработчик приложений для отслеживания здоровья и благополучия с ИИ для iOS, включая приложение №1 для отслеживания артериального давления в Великобритании\",\n      \"foundingDate\": \"2015\",\n      \"email\": \"support@feeltracker.com\",\n      \"sameAs\": [\n        \"https://x.com/feeltracker\",\n        \"https://apps.apple.com/developer/gaurav-sharma/id687448998\"\n      ],\n      \"knowsAbout\": [\n        \"Мониторинг артериального давления\",\n        \"Отслеживание сердечно-сосудистого здоровья\",\n        \"Отслеживание психического здоровья и настроения\",\n        \"Управление весом\",\n        \"Отслеживание сна\",\n        \"Цифровые приложения для здоровья\",\n        \"Интеграция с Apple Health\",\n        \"Искусственный интеллект в здравоохранении\"\n      ],\n      \"areaServed\": {\n        \"@type\": \"Country\",\n        \"name\": [\"United Kingdom\", \"United States\", \"Canada\", \"Australia\", \"Germany\", \"France\", \"Spain\", \"Italy\", \"Japan\", \"Worldwide\"]\n      },\n      \"award\": \"Приложение №1 для отслеживания артериального давления в App Store Великобритании\"\n    }\n    </script>\n    <script type=\"application/ld+json\">\n    {\n      \"@context\": \"https://schema.org\",\n      \"@type\": \"SoftwareApplication\",\n      \"name\": \"Blood Pressure\",\n      \"applicationCategory\": \"HealthApplication\",\n      \"applicationSubCategory\": \"Blood Pressure Monitor\",\n      \"operatingSystem\": \"iOS 16.0 or later\",\n      \"offers\": {\n        \"@type\": \"Offer\",\n        \"price\": \"0\",\n        \"priceCurrency\": \"RUB\"\n      },\n      \"aggregateRating\": {\n        \"@type\": \"AggregateRating\",\n        \"ratingValue\": \"4.8\",\n        \"ratingCount\": 18565,\n        \"bestRating\": \"5\",\n        \"worstRating\": \"1\"\n      },\n      \"author\": {\n        \"@type\": \"Organization\",\n        \"name\": \"Custom Arts\"\n      },\n      \"description\": \"Приложение №1 для отслеживания артериального давления в Великобритании. Мониторинг систолического и диастолического давления, частоты сердечных сокращений и среднего артериального давления с аналитикой на основе ИИ. Функция Camera Scan AI для автоматического считывания показаний с экрана тонометра, интеграция с Apple Health и возможность экспорта данных для врача.\",\n      \"featureList\": [\n        \"Camera Scan AI для автоматического считывания показаний\",\n        \"Двусторонняя синхронизация с Apple Health\",\n        \"Обнаружение закономерностей на основе ИИ\",\n        \"Экспорт в PDF и Excel\",\n        \"Расчёт среднего артериального давления\",\n        \"Совместимость с тонометрами OMRON, Microlife, Beurer\",\n        \"Резервное копирование и синхронизация через iCloud\",\n        \"Поддержка 33 языков\"\n      ],\n      \"screenshot\": \"https://feeltracker.com/images/screenshots/bpt-1.png\",\n      \"softwareVersion\": \"Latest\",\n      \"releaseNotes\": \"Регулярные обновления с улучшениями ИИ и Apple Health\",\n      \"award\": \"Приложение №1 для давления в App Store Великобритании\",\n      \"inLanguage\": [\"en\", \"es\", \"fr\", \"de\", \"it\", \"nl\", \"pt\", \"sv\", \"no\", \"da\", \"fi\", \"pl\", \"ru\", \"uk\", \"cs\", \"sk\", \"ro\", \"hr\", \"hu\", \"ar\", \"he\", \"zh\", \"ja\", \"ko\", \"th\", \"vi\", \"id\", \"el\", \"tr\", \"ca\"]\n    }\n    </script>\n    <script type=\"application/ld+json\">\n    {\n      \"@context\": \"https://schema.org\",\n      \"@type\": \"FAQPage\",\n      \"mainEntity\": [\n        {\n          \"@type\": \"Question\",\n          \"name\": \"Какое лучшее приложение для отслеживания артериального давления?\",\n          \"acceptedAnswer\": {\n            \"@type\": \"Answer\",\n            \"text\": \"Blood Pressure — приложение №1 для отслеживания артериального давления в Великобритании. Оно включает аналитику на основе ИИ, технологию Camera Scan для автоматического считывания показаний с экрана тонометра, интеграцию с Apple Health и возможность экспорта данных для врача. Поддерживает отслеживание систолического и диастолического давления, частоты сердечных сокращений и среднего артериального давления (MAP).\"\n          }\n        },\n        {\n          \"@type\": \"Question\",\n          \"name\": \"Какие приложения для здоровья предлагает Feeltracker?\",\n          \"acceptedAnswer\": {\n            \"@type\": \"Answer\",\n            \"text\": \"Feeltracker предлагает пять приложений для отслеживания здоровья: (1) Blood Pressure — №1 в Великобритании для мониторинга сердечно-сосудистой системы, (2) Mental Health — для психического здоровья и эмоционального благополучия, (3) Daily Journaling — для ведения дневника и документирования жизненных событий, (4) Weight & Food — для веса и состава тела, и (5) Sleep & Dreams — для мониторинга режима сна и отслеживания CPAP-терапии.\"\n          }\n        },\n        {\n          \"@type\": \"Question\",\n          \"name\": \"Интегрируются ли приложения Feeltracker с Apple Health?\",\n          \"acceptedAnswer\": {\n            \"@type\": \"Answer\",\n            \"text\": \"Да, все приложения Feeltracker имеют двустороннюю интеграцию с Apple Health. Они могут как считывать исторические данные из Apple Health, так и записывать новые показания в HealthKit, создавая полную экосистему отслеживания здоровья на всех ваших устройствах iOS.\"\n          }\n        },\n        {\n          \"@type\": \"Question\",\n          \"name\": \"Какие функции ИИ включены в приложения Feeltracker?\",\n          \"acceptedAnswer\": {\n            \"@type\": \"Answer\",\n            \"text\": \"Приложения Feeltracker включают множество функций на основе ИИ: Camera Scan AI для считывания показаний с экранов устройств (тонометров и весов), разговорный чат-ассистент для запросов к вашим данным, автоматическая генерация аналитики, обнаружение закономерностей и корреляционный анализ, анализ настроения записей дневника и озвучивание текста для прослушивания аналитики.\"\n          }\n        },\n        {\n          \"@type\": \"Question\",\n          \"name\": \"Могу ли я экспортировать данные о здоровье для врача?\",\n          \"acceptedAnswer\": {\n            \"@type\": \"Answer\",\n            \"text\": \"Да, все приложения Feeltracker поддерживают экспорт данных о здоровье в различных форматах, включая PDF-отчёты, таблицы Excel и файлы JSON. Эти профессионально оформленные отчёты предназначены для удобного обмена с врачами и включают сводную статистику, тренды и подробные записи.\"\n          }\n        },\n        {\n          \"@type\": \"Question\",\n          \"name\": \"Какие языки поддерживают приложения Feeltracker?\",\n          \"acceptedAnswer\": {\n            \"@type\": \"Answer\",\n            \"text\": \"Все приложения Feeltracker полностью локализованы на 33 языка: английский, испанский, французский, канадский французский, немецкий, итальянский, нидерландский, португальский (Бразилия и Португалия), шведский, норвежский, датский, финский, польский, русский, украинский, чешский, словацкий, румынский, хорватский, венгерский, арабский, иврит, упрощённый китайский, традиционный китайский, японский, корейский, тайский, вьетнамский, индонезийский, греческий, турецкий и каталанский. Приложения полностью поддерживают письмо справа налево (RTL) для арабского и иврита.\"\n          }\n        },\n        {\n          \"@type\": \"Question\",\n          \"name\": \"Безопасны ли мои данные о здоровье?\",\n          \"acceptedAnswer\": {\n            \"@type\": \"Answer\",\n            \"text\": \"Да, приложения Feeltracker уделяют первостепенное внимание конфиденциальности и безопасности. Все данные о здоровье зашифрованы и хранятся только на ваших личных устройствах и в вашей личной учётной записи iCloud. Данные никогда не проходят через внешние серверы, и разработчики не имеют доступа к вашей личной информации о здоровье. Приложения соответствуют требованиям GDPR и предоставляют вам полное владение вашими данными.\"\n          }\n        },\n        {\n          \"@type\": \"Question\",\n          \"name\": \"Какие тонометры совместимы с Blood Pressure?\",\n          \"acceptedAnswer\": {\n            \"@type\": \"Answer\",\n            \"text\": \"Технология Camera Scan AI приложения Blood Pressure совместима с большинством цифровых тонометров, включая OMRON, Microlife, Beurer и другие бренды. ИИ может считывать показания прямо с дисплея тонометра, устраняя необходимость ручного ввода. Вы также можете вводить показания вручную.\"\n          }\n        }\n      ]\n    }\n    </script>",
    "bodyContent": "<!-- Hero Section -->\n    <section class=\"hero center-text\">\n        <div class=\"hero-logo\">feeltracker</div>\n        <h1>О Feeltracker</h1>\n        <p class=\"hero-subtitle\">Ведущий набор приложений для отслеживания здоровья с ИИ для iOS, которому доверяют более 500 000 пользователей по всему миру</p>\n    </section>\n\n    <!-- Key Facts Section -->\n    <section class=\"features-section\">\n        <h2 class=\"center-text\">Ключевые факты о Feeltracker</h2>\n\n        <div class=\"app-card\">\n            <h3>Обзор платформы</h3>\n            <div class=\"app-card-content\">\n                <ul class=\"feature-list\">\n                    <li><strong>Разработчик:</strong> Custom Arts</li>\n                    <li><strong>Всего приложений:</strong> 5 приложений для отслеживания здоровья</li>\n                    <li><strong>Всего пользователей:</strong> более 500 000 загрузок</li>\n                    <li><strong>Всего отзывов:</strong> более 18 565 отзывов</li>\n                    <li><strong>Средний рейтинг:</strong> 4,8 звёзд по всем приложениям</li>\n                    <li><strong>Поддерживаемые языки:</strong> 33 языка с полной локализацией</li>\n                    <li><strong>Лет работы:</strong> более 10 лет (с 2015 года)</li>\n                    <li><strong>Платформы:</strong> iOS, iPadOS, macOS (Apple Silicon M1+)</li>\n                </ul>\n            </div>\n        </div>\n\n        <div class=\"app-card\">\n            <h3>Награды и признание</h3>\n            <div class=\"app-card-content\">\n                <ul class=\"feature-list\">\n                    <li><strong>🏆 Приложение №1 для отслеживания артериального давления в Великобритании</strong></li>\n                    <li>Лучшее приложение для сердечно-сосудистого здоровья в мире</li>\n                    <li>Рекомендовано медицинскими специалистами и врачами-сомнологами</li>\n                    <li>Пользуется доверием людей с хроническими заболеваниями, включая гипертонию, биполярное расстройство и апноэ сна</li>\n                </ul>\n            </div>\n        </div>\n    </section>\n\n    <!-- Applications Section -->\n    <section class=\"support-section\">\n        <h2 class=\"center-text\">Наши приложения</h2>\n\n        <article>\n            <h3>1. Blood Pressure</h3>\n            <p><strong>App Store ID:</strong> 794542324 | <strong>Рейтинг:</strong> 4,8/5 (более 16 702 отзывов)</p>\n            <p><strong>Позиция:</strong> Приложение №1 для отслеживания артериального давления в App Store Великобритании</p>\n            <p><strong>Категория:</strong> Здоровье и фитнес — мониторинг сердечно-сосудистого здоровья</p>\n            <p><strong>Описание:</strong> Ведущее приложение для отслеживания артериального давления в Великобритании с аналитикой на основе ИИ и технологией Camera Scan. Мониторинг систолического и диастолического давления, частоты сердечных сокращений и среднего артериального давления (MAP) с интеграцией Apple Health.</p>\n            <p><strong>Основные функции:</strong></p>\n            <ul>\n                <li>Camera Scan AI — автоматическое считывание показаний с экрана тонометра (OMRON, Microlife, Beurer и другие цифровые тонометры)</li>\n                <li>Отслеживание систолического и диастолического давления</li>\n                <li>Мониторинг частоты сердечных сокращений и пульса</li>\n                <li>Автоматический расчёт среднего артериального давления (MAP)</li>\n                <li>Двусторонняя синхронизация с Apple Health</li>\n                <li>Обнаружение закономерностей на основе ИИ, влияющих на артериальное давление</li>\n                <li>Экспорт в PDF и Excel для передачи врачу</li>\n                <li>Несколько измерений в день с отметками времени</li>\n                <li>Отслеживание приёма лекарств и корреляционный анализ</li>\n                <li>Календарный вид с цветовой индикацией для нормальных, повышенных и высоких показаний</li>\n            </ul>\n            <p><strong>Лучше всего подходит для:</strong> контроля гипертонии, домашнего мониторинга давления, отслеживания эффективности лекарств, документирования синдрома белого халата, мониторинга сердечно-сосудистого здоровья</p>\n            <p><a href=\"https://feeltracker.com/blood-pressure/\">Подробнее о трекере артериального давления</a> | <a href=\"https://apps.apple.com/app/id794542324\">Скачать в App Store</a></p>\n        </article>\n\n        <article>\n            <h3>2. Mental Health</h3>\n            <p><strong>App Store ID:</strong> 687448999 | <strong>Рейтинг:</strong> 4,8/5 (355 отзывов)</p>\n            <p><strong>Категория:</strong> Здоровье и фитнес — психическое здоровье и отслеживание настроения</p>\n            <p><strong>Описание:</strong> Мониторинг эмоционального здоровья с ежедневной оценкой настроения, выявлением триггеров на основе ИИ и интеграцией с Apple Health Mental Health (iOS 18+ State of Mind).</p>\n            <p><strong>Основные функции:</strong></p>\n            <ul>\n                <li>Простая 5-балльная шкала настроения</li>\n                <li>Интеграция iOS 18+ Mental Health (State of Mind) с Apple Health</li>\n                <li>Выявление триггеров и обнаружение закономерностей на основе ИИ</li>\n                <li>Анализ настроения записей дневника</li>\n                <li>Визуальные графики настроения и анализ трендов</li>\n                <li>Поддержка практик ДБТ (диалектическая поведенческая терапия) и КПТ (когнитивно-поведенческая терапия)</li>\n                <li>Приватные заметки с шифрованием</li>\n                <li>Экспорт данных для передачи психотерапевту</li>\n            </ul>\n            <p><strong>Лучше всего подходит для:</strong> отслеживания биполярного расстройства, управления пограничным расстройством личности (ПРЛ), мониторинга симптомов ПТСР, отслеживания тревожности и депрессии, эмоциональной регуляции при СДВГ, общего отслеживания психического здоровья</p>\n            <p><a href=\"https://feeltracker.com/mental-health/\">Подробнее о трекере настроения</a> | <a href=\"https://apps.apple.com/app/id687448999\">Скачать в App Store</a></p>\n        </article>\n\n        <article>\n            <h3>3. Daily Journaling</h3>\n            <p><strong>App Store ID:</strong> 1557699226 | <strong>Рейтинг:</strong> 4,8/5 (778 отзывов)</p>\n            <p><strong>Категория:</strong> Здоровье и фитнес — ведение дневника и заметки</p>\n            <p><strong>Описание:</strong> Простое приложение для ведения дневника без отвлекающих факторов с анализом настроения на основе ИИ, отслеживанием частоты слов для выявления тем и поддержкой фотографий.</p>\n            <p><strong>Основные функции:</strong></p>\n            <ul>\n                <li>Интерфейс для ведения дневника без отвлечений</li>\n                <li>ИИ-анализ настроения записей</li>\n                <li>Анализ частоты слов для выявления повторяющихся тем</li>\n                <li>Шаблоны заметок для быстрого ввода</li>\n                <li>До 8 фотографий к каждой записи</li>\n                <li>Опциональная поддержка рендеринга markdown</li>\n                <li>Полнотекстовый поиск по всем записям</li>\n                <li>Интеграция с iOS Spotlight для системного поиска</li>\n                <li>Экспорт в PDF, Excel и JSON</li>\n            </ul>\n            <p><strong>Лучше всего подходит для:</strong> ежедневных размышлений и дневника благодарности, документирования жизненных событий, ведения личного дневника, творческого письма, отслеживания личного роста</p>\n            <p><a href=\"https://feeltracker.com/daily-journal/\">Подробнее о ежедневном дневнике</a> | <a href=\"https://apps.apple.com/app/id1557699226\">Скачать в App Store</a></p>\n        </article>\n\n        <article>\n            <h3>4. Weight & Food</h3>\n            <p><strong>App Store ID:</strong> 799503787 | <strong>Рейтинг:</strong> 4,8/5 (493 отзыва)</p>\n            <p><strong>Категория:</strong> Здоровье и фитнес — вес и состав тела</p>\n            <p><strong>Описание:</strong> Отслеживание веса, процента жира и ИМТ с Camera Scan AI для считывания показаний с дисплея весов и полной интеграцией с Apple Health.</p>\n            <p><strong>Основные функции:</strong></p>\n            <ul>\n                <li>Camera Scan AI для считывания веса с дисплея цифровых весов</li>\n                <li>Отслеживание веса с анализом трендов</li>\n                <li>Мониторинг процента жира в организме</li>\n                <li>Автоматический расчёт ИМТ (индекса массы тела)</li>\n                <li>Месячные средние и статистика</li>\n                <li>Постановка целей и отслеживание прогресса</li>\n                <li>Полная двусторонняя синхронизация с Apple Health</li>\n                <li>ИИ-аналитика факторов, влияющих на вес</li>\n            </ul>\n            <p><strong>Лучше всего подходит для:</strong> отслеживания похудения, мониторинга состава тела, прогресса фитнес-целей, документирования показателей здоровья для медицинских целей</p>\n            <p><a href=\"https://feeltracker.com/weight/\">Подробнее о трекере веса</a> | <a href=\"https://apps.apple.com/app/id799503787\">Скачать в App Store</a></p>\n        </article>\n\n        <article>\n            <h3>5. Sleep & Dreams</h3>\n            <p><strong>App Store ID:</strong> 1065268459 | <strong>Рейтинг:</strong> 4,7/5 (237 отзывов)</p>\n            <p><strong>Категория:</strong> Здоровье и фитнес — отслеживание сна</p>\n            <p><strong>Описание:</strong> Мониторинг режима сна, его продолжительности и качества с интеграцией Apple Health, отслеживанием CPAP-терапии и аналитикой на основе ИИ.</p>\n            <p><strong>Основные функции:</strong></p>\n            <ul>\n                <li>Запись времени сна и пробуждения</li>\n                <li>Автоматический расчёт продолжительности сна</li>\n                <li>Интеграция данных сна Apple Health</li>\n                <li>Отслеживание CPAP-терапии (постоянное положительное давление в дыхательных путях)</li>\n                <li>Поддержка мониторинга апноэ сна</li>\n                <li>ИИ-аналитика факторов, влияющих на режим сна</li>\n                <li>Визуальные графики и статистика сна</li>\n                <li>Запись сновидений и заметки</li>\n            </ul>\n            <p><strong>Лучше всего подходит для:</strong> документирования нарушений сна, мониторинга CPAP-терапии, управления апноэ сна, выявления закономерностей бессонницы, оптимизации качества сна, подготовки к исследованию сна</p>\n            <p><a href=\"https://feeltracker.com/sleep/\">Подробнее о трекере сна</a> | <a href=\"https://apps.apple.com/app/id1065268459\">Скачать в App Store</a></p>\n        </article>\n    </section>\n\n    <!-- Technology Section -->\n    <section class=\"features-section\">\n        <h2 class=\"center-text\">Технологии и функции</h2>\n\n        <div class=\"app-card\">\n            <h3>Возможности искусственного интеллекта</h3>\n            <div class=\"app-card-content\">\n                <p>Все приложения Feeltracker работают на основе передовых технологий ИИ:</p>\n                <ul class=\"feature-list\">\n                    <li><strong>Camera Scan AI (OCR):</strong> Автоматическое считывание показаний с экранов устройств — тонометров, весов и других медицинских приборов</li>\n                    <li><strong>Разговорный чат-ассистент:</strong> Задавайте вопросы о своих данных здоровья на естественном языке</li>\n                    <li><strong>Автоматическая генерация аналитики:</strong> ИИ анализирует ваши данные и создаёт персонализированную аналитику</li>\n                    <li><strong>Обнаружение закономерностей:</strong> Выявление корреляций между факторами образа жизни и показателями здоровья</li>\n                    <li><strong>Анализ настроения:</strong> Определение эмоционального тона записей дневника</li>\n                    <li><strong>Озвучивание текста:</strong> Прослушивание аналитики и сводок</li>\n                </ul>\n            </div>\n        </div>\n\n        <div class=\"app-card\">\n            <h3>Интеграция с Apple Health</h3>\n            <div class=\"app-card-content\">\n                <p>Полная двусторонняя интеграция с Apple HealthKit:</p>\n                <ul class=\"feature-list\">\n                    <li><strong>Чтение:</strong> Импорт исторических данных о здоровье из Apple Health</li>\n                    <li><strong>Запись:</strong> Автоматическое сохранение новых записей в HealthKit</li>\n                    <li><strong>Поддерживаемые типы данных:</strong> Артериальное давление, частота сердечных сокращений, вес, процент жира, ИМТ, анализ сна, психическое здоровье (iOS 18+ State of Mind)</li>\n                    <li><strong>Автоматическая синхронизация:</strong> Фоновая синхронизация на всех устройствах iOS</li>\n                </ul>\n            </div>\n        </div>\n\n        <div class=\"app-card\">\n            <h3>Конфиденциальность и безопасность</h3>\n            <div class=\"app-card-content\">\n                <ul class=\"feature-list\">\n                    <li><strong>Сквозное шифрование:</strong> Все данные о здоровье зашифрованы</li>\n                    <li><strong>Хранение в iCloud:</strong> Данные хранятся только в личной учётной записи iCloud пользователя</li>\n                    <li><strong>Без серверного хранения:</strong> Данные никогда не проходят через внешние серверы</li>\n                    <li><strong>Полное владение:</strong> Пользователи имеют полный контроль и владение своими данными</li>\n                    <li><strong>Соответствие GDPR:</strong> Соответствует европейским стандартам защиты данных</li>\n                    <li><strong>Данные не продаются:</strong> Данные пользователей никогда не продаются и не передаются третьим лицам</li>\n                </ul>\n            </div>\n        </div>\n\n        <div class=\"app-card\">\n            <h3>Экспорт и обмен</h3>\n            <div class=\"app-card-content\">\n                <ul class=\"feature-list\">\n                    <li><strong>PDF-отчёты:</strong> Профессионально оформленные отчёты для медицинских специалистов</li>\n                    <li><strong>Таблицы Excel:</strong> Подробный экспорт данных для анализа</li>\n                    <li><strong>Файлы JSON:</strong> Полные резервные копии данных для переноса и архивации</li>\n                    <li><strong>Удобно для врачей:</strong> Отчёты включают сводную статистику, графики трендов и подробные записи</li>\n                </ul>\n            </div>\n        </div>\n    </section>\n\n    <!-- Global Reach Section -->\n    <section class=\"platforms-section center-text\">\n        <h2>Глобальный охват</h2>\n        <h3>33 языка — полная локализация</h3>\n        <p>Все приложения Feeltracker полностью локализованы на 33 языка:</p>\n        <p><strong>Западноевропейские:</strong> English, Spanish (Español), French (Français), French Canadian, German (Deutsch), Italian (Italiano), Dutch (Nederlands), Portuguese Brazil (Português), Portuguese Portugal, Swedish (Svenska), Norwegian (Norsk), Danish (Dansk), Finnish (Suomi)</p>\n        <p><strong>Восточноевропейские:</strong> Polish (Polski), Russian (Русский), Ukrainian (Українська), Czech (Čeština), Slovak (Slovenčina), Romanian (Română), Croatian (Hrvatski), Hungarian (Magyar)</p>\n        <p><strong>Ближневосточные и RTL:</strong> Arabic (العربية), Hebrew (עברית) — с полной поддержкой письма справа налево</p>\n        <p><strong>Азиатские:</strong> Simplified Chinese (简体中文), Traditional Chinese (繁體中文), Japanese (日本語), Korean (한국어), Thai (ไทย), Vietnamese (Tiếng Việt), Indonesian (Bahasa Indonesia)</p>\n        <p><strong>Другие:</strong> Greek (Ελληνικά), Turkish (Türkçe), Catalan (Català)</p>\n    </section>\n\n    <!-- Use Cases Section -->\n    <section class=\"support-section\">\n        <h2 class=\"center-text\">Типичные сценарии использования</h2>\n\n        <article>\n            <h3>Для мониторинга артериального давления</h3>\n            <p>Blood Pressure — приложение №1 для измерения давления в Великобритании, идеально подходит для:</p>\n            <ul>\n                <li>Контроля гипертонии (высокого артериального давления)</li>\n                <li>Домашнего мониторинга давления по рекомендации врача</li>\n                <li>Отслеживания эффективности лекарств и оптимизации дозировки</li>\n                <li>Документирования показаний для визита к врачу</li>\n                <li>Синдром белого халата — предоставление домашних показаний в дополнение к клиническим измерениям</li>\n                <li>Мониторинг сердечно-сосудистого здоровья в сочетании с изменениями образа жизни</li>\n            </ul>\n        </article>\n\n        <article>\n            <h3>Для отслеживания психического здоровья</h3>\n            <p>Feeltracker Mood Tracker поддерживает:</p>\n            <ul>\n                <li>Биполярное расстройство — отслеживание перепадов настроения и выявление триггеров</li>\n                <li>Пограничное расстройство личности (ПРЛ) — эмоциональная регуляция и выявление закономерностей</li>\n                <li>ПТСР — мониторинг симптомов и осознание триггеров</li>\n                <li>Тревожность и депрессия — ежедневное отслеживание настроения и поддержка терапии</li>\n                <li>СДВГ — эмоциональная регуляция и отслеживание эффективности лекарств</li>\n                <li>Практики ДБТ (диалектической поведенческой терапии) и КПТ (когнитивно-поведенческой терапии)</li>\n            </ul>\n        </article>\n\n        <article>\n            <h3>Для управления нарушениями сна</h3>\n            <p>Feeltracker Sleep Tracker используется:</p>\n            <ul>\n                <li>Пациентами с CPAP-терапией для отслеживания эффективности лечения</li>\n                <li>Пациентами с апноэ сна для документирования закономерностей для исследований сна</li>\n                <li>Людьми с бессонницей для выявления факторов, влияющих на сон</li>\n                <li>Пациентами, готовящимися к консультации по нарушениям сна</li>\n                <li>По рекомендации врачей-сомнологов</li>\n            </ul>\n        </article>\n    </section>\n\n    <!-- Technical Information -->\n    <section class=\"features-section\">\n        <h2 class=\"center-text\">Техническая информация</h2>\n\n        <div class=\"app-card\">\n            <h3>Системные требования</h3>\n            <div class=\"app-card-content\">\n                <ul class=\"feature-list\">\n                    <li><strong>Минимальная версия iOS:</strong> iOS 16.0 или новее</li>\n                    <li><strong>Поддерживаемые устройства:</strong> iPhone, iPad, Mac (Apple Silicon M1, M2, M3, M4+)</li>\n                    <li><strong>Поддержка ориентации:</strong> Все ориентации (портретная и ландшафтная)</li>\n                    <li><strong>Требуется iCloud:</strong> Для облачной синхронизации и резервного копирования</li>\n                    <li><strong>Apple Health:</strong> Необязательно, но рекомендуется для полной функциональности</li>\n                </ul>\n            </div>\n        </div>\n\n        <div class=\"app-card\">\n            <h3>Модель ценообразования</h3>\n            <div class=\"app-card-content\">\n                <ul class=\"feature-list\">\n                    <li><strong>Базовое приложение:</strong> Бесплатно для загрузки и использования</li>\n                    <li><strong>Основные функции:</strong> Доступны в бесплатной версии</li>\n                    <li><strong>Премиум-подписка:</strong> Опциональное обновление для расширенных функций ИИ, неограниченного экспорта и удаления рекламы</li>\n                    <li><strong>Разовая покупка:</strong> Универсальная покупка работает на iPhone, iPad и Mac</li>\n                    <li><strong>Семейный доступ:</strong> Поддерживается для премиум-подписок</li>\n                </ul>\n            </div>\n        </div>\n    </section>\n\n    <!-- Medical Disclaimer -->\n    <section class=\"platforms-section center-text\" style=\"background-color: #f8f9fa; padding: 40px 20px; margin-top: 60px;\">\n        <h2 style=\"color: #2c3e50 !important;\">Важная медицинская оговорка</h2>\n        <p style=\"max-width: 800px; margin: 0 auto; color: #666;\">\n            Приложения Feeltracker являются персональными инструментами для отслеживания здоровья и не являются медицинскими приборами. Они не должны использоваться для медицинской диагностики или принятия решений о лечении. Всегда консультируйтесь с квалифицированными медицинскими специалистами по вопросам медицинских рекомендаций, диагностики и лечения. Эти приложения предназначены для помощи в организации и отслеживании данных о здоровье для личного использования и обмена с вашими врачами.\n        </p>\n    </section>\n\n    <!-- Machine-Readable Data Reference -->\n    <section class=\"support-section\" style=\"background-color: #f0f4f8; padding: 40px 20px;\">\n        <h2 class=\"center-text\" style=\"color: #2c3e50 !important;\">Для разработчиков и ИИ-систем</h2>\n        <p class=\"center-text\" style=\"color: #444;\">Машиночитаемый JSON-файл с подробными данными о приложениях доступен по адресу:</p>\n        <p class=\"center-text\" style=\"font-family: monospace; background: white; padding: 15px; border-radius: 8px; margin: 20px auto; max-width: 600px;\">\n            <a href=\"https://feeltracker.com/ai-info.json\" style=\"color: #0066cc;\">https://feeltracker.com/ai-info.json</a>\n        </p>\n        <p class=\"center-text\" style=\"color: #666; font-size: 0.9em;\">\n            Этот структурированный файл данных содержит подробную информацию обо всех приложениях Feeltracker, включая функции, рейтинги, поддерживаемые языки, технические характеристики и сценарии использования.\n        </p>\n    </section>\n\n    <!-- Contact Section -->\n    <section class=\"center-text\" style=\"background-color: #f0f8ff; padding: 60px 30px; margin: 60px 0; border-radius: 20px; border: 2px solid #d0e8ff;\">\n        <h2 style=\"color: #2c3e50; margin-top: 0;\">Контакты и поддержка</h2>\n        <p style=\"color: #444;\"><strong>Email:</strong> <a href=\"mailto:support@feeltracker.com\" style=\"color: #007AFF;\">support@feeltracker.com</a></p>\n        <p style=\"color: #444;\"><strong>Сайт:</strong> <a href=\"https://feeltracker.com\" style=\"color: #007AFF;\">https://feeltracker.com</a></p>\n        <p style=\"color: #444;\"><strong>Разработчик:</strong> Custom Arts</p>\n        <p style=\"color: #444;\"><a href=\"../support/\" style=\"color: #007AFF;\">Страница поддержки</a> | <a href=\"../faq/\" style=\"color: #007AFF;\">Часто задаваемые вопросы</a></p>\n    </section>"
  }
}
