{
  "template": "tips-page",
  "lang": "zh",
  "slug": "sleep",
  "path": "sleep/tips",
  "outputPath": "zh/sleep/tips/index.html",
  "appId": "1065268459",
  "data": {
    "appId": "1065268459",
    "meta": {
      "title": "20个睡眠与梦境技巧 - 改善睡眠专家指南 | Feeltracker",
      "description": "通过20个专家技巧掌握睡眠质量，涵盖更好的睡眠、CPAP治疗、睡眠呼吸暂停管理和睡眠卫生。基于证据的恢复性休息和健康策略。",
      "keywords": "睡眠技巧,CPAP治疗,睡眠呼吸暂停,睡眠卫生,睡眠质量,失眠,睡眠追踪,恢复性睡眠,睡眠障碍,改善睡眠",
      "ogTitle": "20个睡眠与梦境技巧 | Feeltracker",
      "ogDescription": "关于改善睡眠、CPAP治疗、睡眠呼吸暂停管理和睡眠卫生的专家技巧，基于证据的策略。",
      "ogImage": "https://feeltracker.com/images/ST_1024.png",
      "twitterDescription": "关于改善睡眠和CPAP治疗的专家技巧。"
    },
    "structuredDataHtml": "    <script type=\"application/ld+json\">\n    {\n      \"@context\": \"https://schema.org\",\n      \"@type\": \"Article\",\n      \"headline\": \"20 Expert Sleep and CPAP Therapy Tips\",\n      \"description\": \"Comprehensive guide to sleep quality, CPAP therapy, sleep apnea management, and sleep hygiene with evidence-based strategies.\",\n      \"author\": {\n        \"@type\": \"Organization\",\n        \"name\": \"Custom Arts\"\n      },\n      \"publisher\": {\n        \"@type\": \"Organization\",\n        \"name\": \"Feeltracker\",\n        \"logo\": {\n          \"@type\": \"ImageObject\",\n          \"url\": \"https://feeltracker.com/images/ST_1024.png\"\n        }\n      },\n      \"datePublished\": \"2025-01-15\",\n      \"dateModified\": \"2025-01-15\"\n    }\n    </script>",
    "conversionEvent": {
      "sendTo": "AW-1066893004/tVcSCKWbwa4bEMz93fwD",
      "value": "1.0",
      "currency": "GBP"
    },
    "hero": {
      "image": "/images/ST_1024.png",
      "imageAlt": "睡眠与梦境",
      "title": "20个睡眠质量与CPAP治疗专家技巧",
      "subtitle": "通过基于证据的睡眠卫生、CPAP依从性、睡眠呼吸暂停管理和最佳睡眠健康策略，实现恢复性睡眠"
    },
    "tipCategories": [
      {
        "title": "睡眠卫生基础",
        "tips": [
          {
            "icon": "fas fa-clock",
            "title": "1. 保持规律的睡眠时间",
            "content": "每天（包括周末）在相同的时间就寝和起床。[研究表明](https://www.ncbi.nlm.nih.gov/pmc/articles/PMC6267703/)，规律的睡眠-觉醒时间能增强昼夜节律，比不规律地延长睡眠时间更能改善睡眠质量。"
          },
          {
            "icon": "fas fa-moon",
            "title": "2. 创造黑暗的睡眠环境",
            "content": "使用遮光窗帘或眼罩。[光线暴露](https://www.ncbi.nlm.nih.gov/pmc/articles/PMC6751071/)会抑制褪黑素的产生并扰乱昼夜节律。即使少量的光线也能降低睡眠质量。"
          },
          {
            "icon": "fas fa-thermometer-half",
            "title": "3. 保持卧室凉爽",
            "content": "将卧室温度保持在15-19°C（60-67°F）之间。睡眠时核心体温自然下降，凉爽的环境[有助于这一过程](https://www.ncbi.nlm.nih.gov/pmc/articles/PMC3427038/)，促进更快入睡和更好的睡眠质量。"
          },
          {
            "icon": "fas fa-volume-mute",
            "title": "4. 减少噪音干扰",
            "content": "使用耳塞、白噪音机或风扇来遮蔽干扰性声音。噪音会打碎睡眠并阻止进入深度恢复阶段，即使您没有意识到自己醒来。"
          },
          {
            "icon": "fas fa-mobile-alt",
            "title": "5. 睡前限制屏幕时间",
            "content": "睡前1-2小时避免使用屏幕。[设备发出的蓝光](https://www.ncbi.nlm.nih.gov/pmc/articles/PMC6751071/)会抑制褪黑素并延迟入睡。如果不可避免使用屏幕，请使用夜间模式或蓝光过滤器。"
          },
          {
            "icon": "fas fa-bed",
            "title": "6. 床只用于睡觉",
            "content": "避免在床上工作、看电视或吃东西。这能加强床与睡眠之间的心理关联，使您躺下时更容易入睡。"
          }
        ]
      },
      {
        "title": "CPAP治疗优化",
        "tips": [
          {
            "icon": "fas fa-head-side-mask",
            "title": "7. 找到合适的面罩",
            "content": "尝试不同的面罩类型（鼻罩、鼻枕、全面罩）找到最适合您的。[合适的面罩](https://www.ncbi.nlm.nih.gov/pmc/articles/PMC5337595/)是CPAP依从性最强的预测因素。漏气和不适是放弃治疗的主要原因。"
          },
          {
            "icon": "fas fa-spray-can",
            "title": "8. 定期清洁CPAP设备",
            "content": "每天用温和的肥皂和水清洗面罩，每周清洁管路，每月更换过滤器。卫生不佳会导致感染、皮肤刺激和设备损耗，从而降低治疗效果。"
          },
          {
            "icon": "fas fa-tint",
            "title": "9. 使用加热加湿器",
            "content": "添加加热加湿器以减少鼻腔干燥、鼻塞和刺激。[加湿功能](https://www.ncbi.nlm.nih.gov/pmc/articles/PMC4623987/)能提高CPAP的耐受性和依从性，尤其是在干燥气候或冬季。"
          },
          {
            "icon": "fas fa-chart-area",
            "title": "10. 监控您的CPAP数据",
            "content": "使用Sleep & Dreams追踪AHI（呼吸暂停-低通气指数）、漏气率和使用时间。监控有助于及早发现问题，并向睡眠医生展示治疗效果。"
          },
          {
            "icon": "fas fa-graduation-cap",
            "title": "11. 练习佩戴面罩",
            "content": "白天清醒时佩戴面罩以适应。练习戴着面罩用鼻子呼吸。逐渐暴露可以减少焦虑并加速适应治疗。"
          },
          {
            "icon": "fas fa-adjust",
            "title": "12. 调整压力渐升设置",
            "content": "使用从较低压力开始逐渐增加的渐升功能。这使入睡更加舒适，同时确保睡眠周期中的治疗压力。"
          }
        ]
      },
      {
        "title": "生活方式与习惯",
        "tips": [
          {
            "icon": "fas fa-coffee",
            "title": "13. 限制咖啡因摄入",
            "content": "睡前6-8小时避免摄入咖啡因。咖啡因的[半衰期为5-6小时](https://www.ncbi.nlm.nih.gov/pmc/articles/PMC5445139/)，这意味着数小时后仍有一半留在体内，影响入睡并减少深度睡眠阶段。"
          },
          {
            "icon": "fas fa-wine-glass",
            "title": "14. 睡前避免饮酒",
            "content": "虽然酒精可能帮助您更快入睡，但它会[打碎睡眠](https://www.ncbi.nlm.nih.gov/pmc/articles/PMC2775419/)、减少REM睡眠，并通过放松喉部肌肉加重睡眠呼吸暂停。睡前3-4小时避免饮酒。"
          },
          {
            "icon": "fas fa-running",
            "title": "15. 定期运动，但注意时间",
            "content": "定期运动能改善睡眠质量，但睡前2-3小时内[避免剧烈运动](https://www.ncbi.nlm.nih.gov/pmc/articles/PMC4341978/)。体力活动会升高体温和兴奋度，使入睡变得困难。"
          },
          {
            "icon": "fas fa-utensils",
            "title": "16. 注意晚餐时间",
            "content": "在睡前2-3小时完成进食。大量、油腻或辛辣的食物会导致消化不适和胃酸反流，干扰睡眠。如果饿了，可以吃少量清淡的零食。"
          },
          {
            "icon": "fas fa-weight",
            "title": "17. 保持健康体重",
            "content": "减肥能显著改善睡眠呼吸暂停。[研究表明](https://www.ncbi.nlm.nih.gov/pmc/articles/PMC3021364/)，肥胖的中重度OSA患者体重减轻10%可使AHI降低26%。"
          },
          {
            "icon": "fas fa-spa",
            "title": "18. 建立放松的睡前习惯",
            "content": "创建30-60分钟的放松程序：阅读、轻柔伸展、冥想或温水浴。[规律的睡前习惯](https://www.ncbi.nlm.nih.gov/pmc/articles/PMC6171441/)向身体发出睡眠即将到来的信号，促进过渡。"
          }
        ]
      },
      {
        "title": "睡眠质量优化",
        "tips": [
          {
            "icon": "fas fa-sun",
            "title": "19. 早晨接受明亮光照",
            "content": "在醒来后30-60分钟内让自己暴露在明亮光线下。[晨间光照](https://www.ncbi.nlm.nih.gov/pmc/articles/PMC6751071/)能固定昼夜节律、提高白天警觉度并改善夜间睡眠质量。"
          },
          {
            "icon": "fas fa-chart-line",
            "title": "20. 追踪和分析您的睡眠模式",
            "content": "使用Sleep & Dreams监测睡眠时长、质量、CPAP使用情况和AHI评分。持续追踪能揭示模式、发现问题并帮助优化您的睡眠策略。与睡眠医生分享数据以进行治疗调整和获得更好的结果。"
          }
        ]
      }
    ],
    "cta": {
      "title": "准备好掌控您的睡眠健康了吗？",
      "subtitle": "下载Sleep & Dreams，立即使用这些专家技巧开始追踪",
      "appStoreUrl": "https://apps.apple.com/us/app/sleep-cpap-feeltracker-st/id1065268459",
      "buttonAlt": "在App Store下载Sleep & Dreams",
      "platformInfo": "适用于iPhone、iPad和Mac"
    },
    "customCss": "\n    .hero h1 {\n        text-align: center;\n    }\n\n    .tips-grid {\n        display: grid;\n        grid-template-columns: repeat(auto-fit, minmax(300px, 1fr));\n        gap: 2rem;\n        margin: 2rem 0 4rem 0;\n    }\n\n    .tip-card {\n        background: #ffffff;\n        padding: 2rem;\n        border-radius: 12px;\n        box-shadow: 0 2px 8px rgba(0,0,0,0.1);\n        transition: transform 0.3s ease, box-shadow 0.3s ease;\n    }\n\n    .tip-card:hover {\n        transform: translateY(-4px);\n        box-shadow: 0 4px 16px rgba(0,0,0,0.15);\n    }\n\n    .tip-icon {\n        font-size: 2.5rem;\n        color: #2B7BD3;\n        margin-bottom: 1rem;\n    }\n\n    .tip-card h3 {\n        color: #2c3e50;\n        font-size: 1.3rem;\n        margin-bottom: 1rem;\n        font-weight: 700;\n    }\n\n    .tip-card p {\n        color: #666;\n        line-height: 1.6;\n        margin: 0;\n    }\n\n    .tip-card a {\n        color: #2B7BD3;\n        text-decoration: none;\n        border-bottom: 1px dotted #2B7BD3;\n    }\n\n    .tip-card a:hover {\n        border-bottom-style: solid;\n    }\n\n    .support-section h2 {\n        margin-top: 3rem;\n        margin-bottom: 1rem;\n    }\n\n    @media (max-width: 768px) {\n        .tips-grid {\n            grid-template-columns: 1fr;\n            gap: 1.5rem;\n        }\n\n        .tip-card {\n            padding: 1.5rem;\n        }\n    }\n\n    @media (prefers-color-scheme: dark) {\n        .tip-card {\n            background: #2d2d2d;\n            box-shadow: 0 2px 8px rgba(0,0,0,0.3);\n        }\n\n        .tip-card:hover {\n            box-shadow: 0 4px 16px rgba(0,0,0,0.4);\n        }\n\n        .tip-icon {\n            color: #5BA4FF;\n        }\n\n        .tip-card h3 {\n            color: #ffffff;\n        }\n\n        .tip-card p {\n            color: #cccccc;\n        }\n\n        .tip-card a {\n            color: #5BA4FF;\n            border-bottom-color: #5BA4FF;\n        }\n\n        .tip-card a:hover {\n            color: #7CB9FF;\n            border-bottom-color: #7CB9FF;\n        }\n    }\n    "
  }
}